icogen_mcp/__init__.py
icogen_mcp/__main__.py
icogen_mcp/server.py
icogen_mcp/service.py
icogen_mcp-0.1.3.dist-info/licenses/LICENSE
icogen_mcp-0.1.3.dist-info/METADATA
icogen_mcp-0.1.3.dist-info/WHEEL
icogen_mcp-0.1.3.dist-info/entry_points.txt
icogen_mcp-0.1.3.dist-info/top_level.txt
icogen_mcp-0.1.3.dist-info/RECORD
