Metadata-Version: 2.4
Name: icogen-mcp
Version: 0.1.3
Summary: A Model Context Protocol (MCP) service for converting PNG files to ICO files with customizable icon dimensions
Author-email: icogen-mcp contributors <maintainer@example.com>
License: MIT
Project-URL: Homepage, https://github.com/username/icogen-mcp
Project-URL: Repository, https://github.com/username/icogen-mcp
Project-URL: Documentation, https://github.com/username/icogen-mcp/blob/main/README.md
Classifier: Development Status :: 3 - Alpha
Classifier: Intended Audience :: Developers
Classifier: License :: OSI Approved :: MIT License
Classifier: Programming Language :: Python :: 3
Classifier: Programming Language :: Python :: 3.8
Classifier: Programming Language :: Python :: 3.9
Classifier: Programming Language :: Python :: 3.10
Classifier: Programming Language :: Python :: 3.11
License-File: LICENSE
Requires-Dist: Pillow>=9.0.0
Requires-Dist: fastmcp>=0.1.0
Requires-Dist: pydantic>=2.0.0
Provides-Extra: dev
Requires-Dist: pytest>=7.0.0; extra == "dev"
Requires-Dist: black>=23.0.0; extra == "dev"
Requires-Dist: flake8>=6.0.0; extra == "dev"
Dynamic: license-file
